llm_serving/__init__.py
llm_serving/inference_services.py
llm_serving-0.0.6.dist-info/licenses/LICENSE
llm_serving-0.0.6.dist-info/METADATA
llm_serving-0.0.6.dist-info/WHEEL
llm_serving-0.0.6.dist-info/top_level.txt
llm_serving-0.0.6.dist-info/RECORD
