Metadata-Version: 2.4
Name: llm_serving
Version: 0.0.6
Summary: A package to perform LLM inference in Solenium/Unergy HQ
Home-page: https://gitlab.com/unergy-dev/ai/llm_serving_module
Author: Unergy/Solenium
Author-email: pablo@solenium.co
Classifier: Programming Language :: Python :: 3
Classifier: License :: OSI Approved :: MIT License
Classifier: Operating System :: OS Independent
License-File: LICENSE
Requires-Dist: requests
Requires-Dist: httpx
Requires-Dist: langchain
Requires-Dist: langchain-core
Dynamic: author
Dynamic: author-email
Dynamic: classifier
Dynamic: description
Dynamic: description-content-type
Dynamic: home-page
Dynamic: license-file
Dynamic: requires-dist
Dynamic: summary
